typescope/__init__.py
typescope/py.typed
typescope-0.0.1.dist-info/METADATA
typescope-0.0.1.dist-info/WHEEL
typescope-0.0.1.dist-info/RECORD
